MANIFEST.in
readme.md
requirements.txt
setup.py
hfpy/__init__.py
hfpy/atp.py
hfpy/atp_pg.py
hfpy/bar.py
hfpy/config.py
hfpy/data.py
hfpy/moniter.py
hfpy/order.py
hfpy/report_stra.py
hfpy/strategy.py
hfpy/structs.py
hfpy/template.html
hfpy.egg-info/PKG-INFO
hfpy.egg-info/SOURCES.txt
hfpy.egg-info/dependency_links.txt
hfpy.egg-info/requires.txt
hfpy.egg-info/top_level.txt