Metadata-Version: 2.1
Name: hfpy
Version: 0.2.2
Summary: Hai Feng Future Trading Platform with SE
Home-page: https://github.com/haifengat/hf_at_py
Author: HaiFeng
Author-email: haifengat@vip.qq.com
License: MIT License
Platform: any
Classifier: Programming Language :: Python :: 3.6
Classifier: Programming Language :: Python :: 3.7
Classifier: License :: OSI Approved :: MIT License
Classifier: Operating System :: OS Independent
Requires-Python: >=3.6.0
